slights-talkie/ApiInterface.py
slights-talkie/ArduinoInterface.py
slights-talkie/Will.py
slights-talkie/__init__.py
slightsTalkie-0.0.4.data/scripts/slightsTalkie
slightsTalkie-0.0.4.data/scripts/strangerapi
slightsTalkie-0.0.4.data/scripts/strangerlights
slightsTalkie-0.0.4.dist-info/DESCRIPTION.rst
slightsTalkie-0.0.4.dist-info/METADATA
slightsTalkie-0.0.4.dist-info/RECORD
slightsTalkie-0.0.4.dist-info/WHEEL
slightsTalkie-0.0.4.dist-info/metadata.json
slightsTalkie-0.0.4.dist-info/top_level.txt
slightstalkie/ApiInterface.py
slightstalkie/ArduinoInterface.py
slightstalkie/Will.py
slightstalkie/__init__.py
