Metadata-Version: 2.0
Name: slightsTalkie
Version: 0.0.4
Summary: Contains libraries to communicate with both the web application api and the arduino serial listener. This allows for sending and retrieving messages from both interfaces. Will.py uses these libraries to inform the arduino serial interface what messages is next in the queue
Home-page: https://github.com/dfresh613/strangerLights
Author: Douglas Rohde
Author-email: douglas.rohde2@gmail.com
License: MIT
Keywords: strangerlights
Platform: UNKNOWN
Classifier: Development Status :: 4 - Beta
Classifier: Topic :: Other/Nonlisted Topic
Classifier: License :: OSI Approved :: MIT License
Classifier: Programming Language :: Python :: 2.7
Requires-Dist: pyserial
Requires-Dist: requests
